azure_lmdc/azure_wrapper_class.py
azure_lmdc/demo.py
azure_lmdc-1.0.5.dist-info/LICENSE
azure_lmdc-1.0.5.dist-info/METADATA
azure_lmdc-1.0.5.dist-info/WHEEL
azure_lmdc-1.0.5.dist-info/entry_points.txt
azure_lmdc-1.0.5.dist-info/top_level.txt
azure_lmdc-1.0.5.dist-info/RECORD
