Metadata-Version: 2.1
Name: azure-lmdc
Version: 1.0.5
Summary: Esta biblioteca tem como objetivo generalizar funções da integração entre Azure e Python utilizando o SDK do Azure
Home-page: UNKNOWN
Author: LMDC-UFF
Author-email: opensource@lmdc.uff.br
License: MIT
Platform: UNKNOWN
Classifier: License :: OSI Approved :: MIT License
Classifier: Programming Language :: Python :: 3
Classifier: Programming Language :: Python :: 3.8
License-File: LICENSE
Requires-Dist: azure-identity (==1.8.0)
Requires-Dist: azure-storage-file-datalake (==12.6.0)
Requires-Dist: Pillow (==9.1.0)
Requires-Dist: python-dotenv (==0.20.0)
